semantic_poetry_demo/__init__.py
semantic_poetry_demo/main.py
semantic_poetry_demo-1.0.1.dist-info/METADATA
semantic_poetry_demo-1.0.1.dist-info/WHEEL
semantic_poetry_demo-1.0.1.dist-info/RECORD
