Metadata-Version: 2.1
Name: semantic-poetry-demo
Version: 1.0.1
Summary: This is a test!
Author: Matteo Fordiani
Author-email: matteofordiani@gmail.com
Requires-Python: >=3.11,<4.0
Classifier: Programming Language :: Python :: 3
Classifier: Programming Language :: Python :: 3.11
Classifier: Programming Language :: Python :: 3.12
Requires-Dist: numpy (>=1.26.4,<2.0.0)
